ratisbona_pygames/__init__.py
ratisbona_pygames/color_blindness_cli/__init__.py
ratisbona_pygames/color_blindness_cli/__main__.py
ratisbona_pygames/color_blindness_cli/_color_blindness_cli.py
ratisbona_pygames/death_by_powerpoint/__init__.py
ratisbona_pygames/death_by_powerpoint/__main__.py
ratisbona_pygames/death_by_powerpoint/_death_by_powerpoint.py
ratisbona_pygames/etchasketch/__init__.py
ratisbona_pygames/etchasketch/__main__.py
ratisbona_pygames/etchasketch/etch_a_sketch.py
ratisbona_pygames/fanedit/__init__.py
ratisbona_pygames/fanedit/__main__.py
ratisbona_pygames/fanedit/_fanedit.py
ratisbona_pygames/fanedit/_fanedit2.py
ratisbona_pygames/fire_demo/__init__.py
ratisbona_pygames/fire_demo/__main__.py
ratisbona_pygames/fire_demo/example.py
ratisbona_pygames/fire_demo/fire.py
ratisbona_pygames/frenchvfd_display_arduino_mega/__init__.py
ratisbona_pygames/frenchvfd_display_arduino_mega/__main__.py
ratisbona_pygames/frenchvfd_display_arduino_mega/_french_vfd.py
ratisbona_pygames/frenchvfd_display_arduino_mega/_vfd_display_cli.py
ratisbona_pygames/gameutils/__init__.py
ratisbona_pygames/gameutils/_canvas.py
ratisbona_pygames/gameutils/_colors.py
ratisbona_pygames/gameutils/_gameutils.py
ratisbona_pygames/gameutils/_lighteffects.py
ratisbona_pygames/gameutils/_textrelated.py
ratisbona_pygames/gameutils/_timeing.py
ratisbona_pygames/joystick_demo/__init__.py
ratisbona_pygames/joystick_demo/__main__.py
ratisbona_pygames/joystick_demo/_joystick_demo.py
ratisbona_pygames/palette_demo/__init__.py
ratisbona_pygames/palette_demo/__main__.py
ratisbona_pygames/palette_demo/_palette_painter.py
ratisbona_pygames/speedometer/__init__.py
ratisbona_pygames/speedometer/__main__.py
ratisbona_pygames/speedometer/_speedometer.py
ratisbona_pygames-0.0.4.dist-info/METADATA
ratisbona_pygames-0.0.4.dist-info/WHEEL
ratisbona_pygames-0.0.4.dist-info/entry_points.txt
ratisbona_pygames-0.0.4.dist-info/licenses/LICENSE
ratisbona_pygames-0.0.4.dist-info/RECORD
