Metadata-Version: 2.4
Name: ratisbona_pygames
Version: 0.0.4
Summary: A Collection of demos and small games for the pygame library.
Project-URL: Homepage, https://sourceforge.net/projects/kevins-pygames/
Author-email: Ulrich Schwenk <ulrich-schwenk@gmx.de>
License-File: LICENSE
Classifier: License :: OSI Approved :: GNU Lesser General Public License v2 (LGPLv2)
Classifier: Operating System :: OS Independent
Classifier: Programming Language :: Python :: 3
Requires-Python: >=3.10
Requires-Dist: click
Requires-Dist: numpy
Requires-Dist: psutil
Requires-Dist: pygame
Requires-Dist: pyqt6
Requires-Dist: pyserial
Requires-Dist: ratisbona-utils>=0.0.4
Requires-Dist: scipy
Provides-Extra: dev
Requires-Dist: black[d]; extra == 'dev'
Requires-Dist: coverage; extra == 'dev'
Requires-Dist: mypy; extra == 'dev'
Requires-Dist: poethepoet; extra == 'dev'
Requires-Dist: pylint; extra == 'dev'
Requires-Dist: twine; extra == 'dev'
